lexer/__init__.py
lexer/core.py
lexer/data/example.txt
lexer_nlp-0.1.0.dist-info/METADATA
lexer_nlp-0.1.0.dist-info/WHEEL
lexer_nlp-0.1.0.dist-info/top_level.txt
lexer_nlp-0.1.0.dist-info/RECORD
