Metadata-Version: 2.1
Name: lexer-nlp
Version: 0.1.0
Summary: A Python package to display text/docs in the terminal.
Author: SeventyThree
Author-email: 73@gmail.com
Classifier: Programming Language :: Python :: 3
Classifier: License :: OSI Approved :: MIT License
Classifier: Operating System :: OS Independent
Requires-Python: >=3.6
